runreport/__init__.py
runreport/runreport.py
runreport-0.1.2.dist-info/METADATA
runreport-0.1.2.dist-info/WHEEL
runreport-0.1.2.dist-info/top_level.txt
runreport-0.1.2.dist-info/RECORD
