Metadata-Version: 2.1
Name: runreport
Version: 0.1.2
Summary: A module to send the contents of the file being executed to a CGI script.
Home-page: https://github.com/davidbpython/runreport
Author: David Blaikie
Author-email: david@davidbpython.com
License: MIT
Platform: UNKNOWN
